kuavo_humanoid_sdk/__init__.py
kuavo_humanoid_sdk/common/logger.py
kuavo_humanoid_sdk/interfaces/__init__.py
kuavo_humanoid_sdk/interfaces/data_types.py
kuavo_humanoid_sdk/interfaces/end_effector.py
kuavo_humanoid_sdk/interfaces/robot.py
kuavo_humanoid_sdk/interfaces/robot_info.py
kuavo_humanoid_sdk/kuavo/__init__.py
kuavo_humanoid_sdk/kuavo/demo_climbstair.py
kuavo_humanoid_sdk/kuavo/dexterous_hand.py
kuavo_humanoid_sdk/kuavo/leju_claw.py
kuavo_humanoid_sdk/kuavo/logger_client.py
kuavo_humanoid_sdk/kuavo/robot.py
kuavo_humanoid_sdk/kuavo/robot_arm.py
kuavo_humanoid_sdk/kuavo/robot_audio.py
kuavo_humanoid_sdk/kuavo/robot_blockly.py
kuavo_humanoid_sdk/kuavo/robot_climbstair.py
kuavo_humanoid_sdk/kuavo/robot_head.py
kuavo_humanoid_sdk/kuavo/robot_info.py
kuavo_humanoid_sdk/kuavo/robot_microphone.py
kuavo_humanoid_sdk/kuavo/robot_navigation.py
kuavo_humanoid_sdk/kuavo/robot_observation.py
kuavo_humanoid_sdk/kuavo/robot_speech.py
kuavo_humanoid_sdk/kuavo/robot_state.py
kuavo_humanoid_sdk/kuavo/robot_tool.py
kuavo_humanoid_sdk/kuavo/robot_vision.py
kuavo_humanoid_sdk/kuavo/core/audio.py
kuavo_humanoid_sdk/kuavo/core/core.py
kuavo_humanoid_sdk/kuavo/core/dex_hand_control.py
kuavo_humanoid_sdk/kuavo/core/leju_claw_control.py
kuavo_humanoid_sdk/kuavo/core/llm_doubao.py
kuavo_humanoid_sdk/kuavo/core/microphone.py
kuavo_humanoid_sdk/kuavo/core/navigation.py
kuavo_humanoid_sdk/kuavo/core/ros_env.py
kuavo_humanoid_sdk/kuavo/core/sdk_deprecated.py
kuavo_humanoid_sdk/kuavo/core/ros/audio.py
kuavo_humanoid_sdk/kuavo/core/ros/camera.py
kuavo_humanoid_sdk/kuavo/core/ros/control.py
kuavo_humanoid_sdk/kuavo/core/ros/microphone.py
kuavo_humanoid_sdk/kuavo/core/ros/navigation.py
kuavo_humanoid_sdk/kuavo/core/ros/observation.py
kuavo_humanoid_sdk/kuavo/core/ros/param.py
kuavo_humanoid_sdk/kuavo/core/ros/sat_utils.py
kuavo_humanoid_sdk/kuavo/core/ros/state.py
kuavo_humanoid_sdk/kuavo/core/ros/tools.py
kuavo_humanoid_sdk/kuavo/core/ros/vision.py
kuavo_humanoid_sdk-1.3.0.dist-info/METADATA
kuavo_humanoid_sdk-1.3.0.dist-info/WHEEL
kuavo_humanoid_sdk-1.3.0.dist-info/top_level.txt
kuavo_humanoid_sdk-1.3.0.dist-info/RECORD
